livekit/plugins/rime/__init__.py
livekit/plugins/rime/langs.py
livekit/plugins/rime/log.py
livekit/plugins/rime/models.py
livekit/plugins/rime/py.typed
livekit/plugins/rime/tts.py
livekit/plugins/rime/version.py
livekit_plugins_rime-1.3.11.dist-info/METADATA
livekit_plugins_rime-1.3.11.dist-info/WHEEL
livekit_plugins_rime-1.3.11.dist-info/RECORD
